uppercase_converter/__init__.py
uppercase_converter/converter.py
UppercaseConverter-1.0.0.dist-info/LICENSE
UppercaseConverter-1.0.0.dist-info/METADATA
UppercaseConverter-1.0.0.dist-info/WHEEL
UppercaseConverter-1.0.0.dist-info/entry_points.txt
UppercaseConverter-1.0.0.dist-info/top_level.txt
UppercaseConverter-1.0.0.dist-info/RECORD
